elevenlabs/__init__.py
elevenlabs/client.py
elevenlabs/core/__init__.py
elevenlabs/core/api_error.py
elevenlabs/core/client_wrapper.py
elevenlabs/core/datetime_utils.py
elevenlabs/core/jsonable_encoder.py
elevenlabs/core/remove_none_from_dict.py
elevenlabs/errors/__init__.py
elevenlabs/errors/unprocessable_entity_error.py
elevenlabs/py.typed
elevenlabs/resources/__init__.py
elevenlabs/resources/audio_native/__init__.py
elevenlabs/resources/audio_native/client.py
elevenlabs/resources/history/__init__.py
elevenlabs/resources/history/client.py
elevenlabs/resources/models/__init__.py
elevenlabs/resources/models/client.py
elevenlabs/resources/projects/__init__.py
elevenlabs/resources/projects/client.py
elevenlabs/resources/projects/resources/__init__.py
elevenlabs/resources/projects/resources/chapters/__init__.py
elevenlabs/resources/projects/resources/chapters/client.py
elevenlabs/resources/projects/resources/chapters/resources/__init__.py
elevenlabs/resources/projects/resources/chapters/resources/snapshots/__init__.py
elevenlabs/resources/projects/resources/chapters/resources/snapshots/client.py
elevenlabs/resources/pronunciation_dictionary/__init__.py
elevenlabs/resources/pronunciation_dictionary/client.py
elevenlabs/resources/samples/__init__.py
elevenlabs/resources/samples/client.py
elevenlabs/resources/text_to_speech/__init__.py
elevenlabs/resources/text_to_speech/client.py
elevenlabs/resources/user/__init__.py
elevenlabs/resources/user/client.py
elevenlabs/resources/voices/__init__.py
elevenlabs/resources/voices/client.py
elevenlabs/types/__init__.py
elevenlabs/types/add_project_response_model.py
elevenlabs/types/add_pronunciation_dictionary_response_model.py
elevenlabs/types/add_voice_response_model.py
elevenlabs/types/audio_native_create_project_response_model.py
elevenlabs/types/audio_native_get_embed_code_response_model.py
elevenlabs/types/chapter_response_model.py
elevenlabs/types/chapter_response_model_state.py
fern_elevenlabs-0.0.4.dist-info/METADATA
fern_elevenlabs-0.0.4.dist-info/WHEEL
fern_elevenlabs-0.0.4.dist-info/RECORD
